[{
        "id": 1,
        "imgSrc": "https://wx3.sinaimg.cn/mw690/8a1b908fly1g2vgox0cvxj20qo0qojsy.jpg",
        "title": "老妈生日快乐",
        "description": "老妈生日快乐！虽然每过一次生日就又年长一岁，但是它能让你看到一年一年真实的在生活着，而不是稀里糊涂的过着。而且，今天你的儿女都来祝你生日快乐，会很快乐啊！快乐的时光会盖过所有的不快乐！老妈，今天早点回家做点好吃的啊",
        "author": "小英，小松"
    },
    {
        "id": 2,
        "imgSrc": "https://wx3.sinaimg.cn/mw690/8a1b908fly1g2vgox54ygj20u01407cy.jpg",
        "title": "老妈我爱你",
        "description": "小时候总是和老妈吵，吵吵闹闹的长大的。后来又有一些抱怨，见面了还是会争吵。现在年过30了，知道父母的不易，事实上是每个人只是活着就已经很不容易了。所以要做的是感恩，感恩母亲生下了我，把我养大。感恩父母现在都还健在，身体没有大毛病。这样，爸妈都能活到100岁了，我们还可以在一起好多年。只要父母在，我们永远都是幸福的孩子！",
        "author": "你的贴心小儿子"
    },
    {
        "id": 3,
        "imgSrc": "https://wx3.sinaimg.cn/mw1024/8a1b908fly1g2vgv5bvdwj20lw0sc42i.jpg",
        "title": "往后的路一起走！",
        "description": "以前我总是没有安全感，可能现在安全感也不多，这也许是一方水土一方人，河南人的通病；我总觉得站在悬崖峭壁上，身后没有支撑，孤独的时候不知道跟谁说怕透漏自己的心事别人更看不起；妈妈，我们之间或许真的需要更多的沟通，我们母女的缘分不应该这样浅，往后的路，我们互相搀扶，慢慢走~",
        "author": "你的宝贝大女儿"
    },
    {
        "id": 4,
        "imgSrc": "https://wx2.sinaimg.cn/mw1024/8a1b908fly1g2vgu5qtxpj20u0140kjp.jpg",
        "title": "每天都要快乐哟！",
        "description": "看到这张照片开不开心？以后不开心时，看看这张照片就开心了。希望我们一家人都平平安安，快快乐乐！一家人在一起，就是天伦！  这个网页做了一周啊，我最近一直都是在学做网页呢，这是第一个成果，给老妈的生日礼物！！",
        "author": "小英，小松"
    }
]